hydra_slayer/__init__.py
hydra_slayer/factory.py
hydra_slayer/functional.py
hydra_slayer/registry.py
hydra_slayer-0.5.0.dist-info/LICENSE
hydra_slayer-0.5.0.dist-info/METADATA
hydra_slayer-0.5.0.dist-info/WHEEL
hydra_slayer-0.5.0.dist-info/RECORD
