Metadata-Version: 2.1
Name: hydra-slayer
Version: 0.5.0
Summary: A framework for elegantly configuring complex applications
Home-page: https://catalyst-team.github.io/hydra-slayer/
License: Apache-2.0
Keywords: distributed computing
Author: Sergey Kolesnikov
Author-email: scitator@gmail.com
Requires-Python: >=3.7,<4.0
Classifier: Development Status :: 4 - Beta
Classifier: Environment :: Console
Classifier: Intended Audience :: Developers
Classifier: Intended Audience :: Science/Research
Classifier: License :: OSI Approved :: Apache Software License
Classifier: Natural Language :: English
Classifier: Operating System :: OS Independent
Classifier: Programming Language :: Python
Classifier: Programming Language :: Python :: 3
Classifier: Programming Language :: Python :: 3.7
Classifier: Programming Language :: Python :: 3.8
Classifier: Programming Language :: Python :: 3.9
Classifier: Programming Language :: Python :: 3.10
Classifier: Programming Language :: Python :: 3.11
Classifier: Programming Language :: Python :: 3.12
Classifier: Programming Language :: Python :: Implementation :: CPython
Classifier: Topic :: Scientific/Engineering :: Information Analysis
Project-URL: Documentation, https://catalyst-team.github.io/hydra-slayer/
Project-URL: Repository, https://github.com/catalyst-team/hydra-slayer
